prompt4all_liteon/__init__.py
prompt4all_liteon/app.py
prompt4all_liteon/context.py
prompt4all_liteon/gradio_css.py
prompt4all_liteon/theme.py
prompt4all_liteon/api/__init__.py
prompt4all_liteon/api/base_api.py
prompt4all_liteon/api/context_type.py
prompt4all_liteon/utils/__init__.py
prompt4all_liteon/utils/chatgpt_utils.py
prompt4all_liteon/utils/io_utils.py
prompt4all_liteon/utils/pdf_utils.py
prompt4all_liteon/utils/regex_utils.py
prompt4all_liteon/utils/summary_utils.py
prompt4all_liteon/utils/tokens_utils.py
prompt4all_liteon/utils/whisper_utils.py
prompt4all_liteon-0.0.3.dist-info/LICENSE
prompt4all_liteon-0.0.3.dist-info/METADATA
prompt4all_liteon-0.0.3.dist-info/WHEEL
prompt4all_liteon-0.0.3.dist-info/top_level.txt
prompt4all_liteon-0.0.3.dist-info/RECORD
