Metadata-Version: 2.1
Name: prompt4all-liteon
Version: 0.0.3
Summary: Prompt is all you need
Download-URL: https://test.pypi.org/project/prompt4all_liteon
Author: Allan Yiin
Author-email: allanyiin.ai@gmail.com
License: MIT
Keywords: chatgpt,gpt4
Classifier: Development Status :: 4 - Beta
Classifier: Intended Audience :: Developers
Classifier: Intended Audience :: Education
Classifier: Intended Audience :: Science/Research
Classifier: License :: OSI Approved :: MIT License
Classifier: Programming Language :: Python :: 3.7
Classifier: Programming Language :: Python :: 3.8
Classifier: Programming Language :: Python :: 3.9
Classifier: Topic :: Software Development :: Libraries
Classifier: Topic :: Software Development :: Libraries :: Python Modules
Requires-Python: >=3.7
License-File: LICENSE
Requires-Dist: asyncio (>=3.4.3)
Requires-Dist: beautifulsoup4 (>=4.11.1)
Requires-Dist: gradio (>=3.35.0)
Requires-Dist: latex2mathml
Requires-Dist: Markdown
Requires-Dist: markdown2 (>=2.4.8)
Requires-Dist: nest-asyncio
Requires-Dist: numpy (>=1.23.5)
Requires-Dist: openai (>=0.27.8)
Requires-Dist: opencv-python (>=4.7.0.68)
Requires-Dist: pillow (>=9.4.0)
Requires-Dist: pytube (>=12.1.2)
Requires-Dist: pydub (>=0.25.1)
Requires-Dist: pypdf (>=3.7.1)
Requires-Dist: regex (>=2022.10.31)
Requires-Dist: requests (>=2.31.0)
Requires-Dist: soundfile (>=0.7)
Requires-Dist: tiktoken (>=0.3.3)
Requires-Dist: moviepy
Requires-Dist: whisper (>=1.1.10)
Requires-Dist: pathlib (>=1.0.1)
Requires-Dist: setuptools (>=67.8.0)
Requires-Dist: torch (>=2.0.0)
Requires-Dist: tqdm (>=4.64.1)
Provides-Extra: tests
Requires-Dist: pytest ; extra == 'tests'
Requires-Dist: pytest-pep8 ; extra == 'tests'
Requires-Dist: pytest-xdist ; extra == 'tests'
Requires-Dist: pytest-cov ; extra == 'tests'
Requires-Dist: requests ; extra == 'tests'
Requires-Dist: markdown ; extra == 'tests'
